{
  "scriptCompleted": true,
  "files": [
    {
      "path": ".ua/.understandignore",
      "language": "unknown",
      "sizeLines": 53,
      "fileCategory": "code"
    },
    {
      "path": "data/metadata/canon_lists.md",
      "language": "markdown",
      "sizeLines": 30,
      "fileCategory": "docs"
    },
    {
      "path": "data/raw/.gitkeep",
      "language": "unknown",
      "sizeLines": 0,
      "fileCategory": "code"
    },
    {
      "path": "docs/historical_notes.md",
      "language": "markdown",
      "sizeLines": 25,
      "fileCategory": "docs"
    },
    {
      "path": "docs/proposal.md",
      "language": "markdown",
      "sizeLines": 51,
      "fileCategory": "docs"
    },
    {
      "path": "notebooks/01_canon_overlap.ipynb",
      "language": "ipynb",
      "sizeLines": 29,
      "fileCategory": "code"
    },
    {
      "path": "notebooks/02_translation_lineage.ipynb",
      "language": "ipynb",
      "sizeLines": 29,
      "fileCategory": "code"
    },
    {
      "path": "notebooks/03_topic_modeling.ipynb",
      "language": "ipynb",
      "sizeLines": 29,
      "fileCategory": "code"
    },
    {
      "path": "notebooks/04_visualization.ipynb",
      "language": "ipynb",
      "sizeLines": 29,
      "fileCategory": "code"
    },
    {
      "path": "outputs/figures/.gitkeep",
      "language": "unknown",
      "sizeLines": 0,
      "fileCategory": "code"
    },
    {
      "path": "README.md",
      "language": "markdown",
      "sizeLines": 52,
      "fileCategory": "docs"
    },
    {
      "path": "requirements.txt",
      "language": "txt",
      "sizeLines": 25,
      "fileCategory": "docs"
    },
    {
      "path": "src/align_corpus.py",
      "language": "python",
      "sizeLines": 39,
      "fileCategory": "code"
    },
    {
      "path": "src/data_loader.py",
      "language": "python",
      "sizeLines": 52,
      "fileCategory": "code"
    },
    {
      "path": "src/graph_builder.py",
      "language": "python",
      "sizeLines": 60,
      "fileCategory": "code"
    }
  ],
  "totalFiles": 15,
  "filteredByIgnore": 0,
  "estimatedComplexity": "small",
  "stats": {
    "filesScanned": 15,
    "byCategory": {
      "code": 10,
      "docs": 5
    },
    "byLanguage": {
      "unknown": 3,
      "markdown": 4,
      "ipynb": 4,
      "txt": 1,
      "python": 3
    }
  }
}